{
    "dialogs": [
        {
            "id": 0,
            "name": "Opening",
            "lines": [
                {
                    "id": 0,
                    "image": null,
                    "message": [
                        "It's hard te be a millenial, you know.",
                        "People just don't take you seriously.",
                        "Even this job is unpayed!",
                        "I need to find a way to make money.",
                        "Maybe I should do some odd jobs in the side.",
                        "I guess I should look for some in the papers."
                    ]
                }
            ]
        }
    ]
}